odoo9_addon_account_invoice_start_end_dates-9.0.1.0.0.99.dev8-py2.7-nspkg.pth
odoo9_addon_account_invoice_start_end_dates-9.0.1.0.0.99.dev8.dist-info/METADATA
odoo9_addon_account_invoice_start_end_dates-9.0.1.0.0.99.dev8.dist-info/RECORD
odoo9_addon_account_invoice_start_end_dates-9.0.1.0.0.99.dev8.dist-info/WHEEL
odoo9_addon_account_invoice_start_end_dates-9.0.1.0.0.99.dev8.dist-info/namespace_packages.txt
odoo9_addon_account_invoice_start_end_dates-9.0.1.0.0.99.dev8.dist-info/top_level.txt
odoo_addons/account_invoice_start_end_dates/README.rst
odoo_addons/account_invoice_start_end_dates/__init__.py
odoo_addons/account_invoice_start_end_dates/__openerp__.py
odoo_addons/account_invoice_start_end_dates/demo/product_demo.xml
odoo_addons/account_invoice_start_end_dates/i18n/account_invoice_start_end_dates.pot
odoo_addons/account_invoice_start_end_dates/i18n/de.po
odoo_addons/account_invoice_start_end_dates/i18n/es.po
odoo_addons/account_invoice_start_end_dates/i18n/fr.po
odoo_addons/account_invoice_start_end_dates/i18n/hr.po
odoo_addons/account_invoice_start_end_dates/i18n/ko_KR.po
odoo_addons/account_invoice_start_end_dates/i18n/nb_NO.po
odoo_addons/account_invoice_start_end_dates/models/__init__.py
odoo_addons/account_invoice_start_end_dates/models/account_invoice.py
odoo_addons/account_invoice_start_end_dates/models/account_move_line.py
odoo_addons/account_invoice_start_end_dates/models/product.py
odoo_addons/account_invoice_start_end_dates/static/description/icon.png
odoo_addons/account_invoice_start_end_dates/tests/__init__.py
odoo_addons/account_invoice_start_end_dates/tests/test_invoice_start_end_dates.py
odoo_addons/account_invoice_start_end_dates/views/account_invoice.xml
odoo_addons/account_invoice_start_end_dates/views/account_move.xml
odoo_addons/account_invoice_start_end_dates/views/product.xml
